aioreadline/__init__.py
aioreadline/aioreadline.py
aioreadline-2024.1.25.dist-info/LICENSE.txt
aioreadline-2024.1.25.dist-info/METADATA
aioreadline-2024.1.25.dist-info/WHEEL
aioreadline-2024.1.25.dist-info/top_level.txt
aioreadline-2024.1.25.dist-info/RECORD
