Metadata-Version: 2.1
Name: aioreadline
Version: 2024.1.25
Summary: async-compatible libreadline wrapper
Author-email: Mario Kicherer <dev@kicherer.org>
License: Permission is hereby granted, free of charge, to any person obtaining a copy
Project-URL: Homepage, https://github.com/anyc/aioreadline/
Project-URL: Issues, https://github.com/anyc/aioreadline/issues
Keywords: readline,ctypes
Classifier: Programming Language :: Python :: 3
Requires-Python: >=3.0
License-File: LICENSE.txt
